replicards/__init__.py
replicards/evo_sim_demo.py
replicards/evo_sim_objects.py
replicards-1.0.0.dist-info/LICENSE
replicards-1.0.0.dist-info/METADATA
replicards-1.0.0.dist-info/WHEEL
replicards-1.0.0.dist-info/top_level.txt
replicards-1.0.0.dist-info/RECORD
