Metadata-Version: 2.1
Name: replicards
Version: 1.0.0
Summary: An interactive way of teaching biological evolution through a card game.
Author: Elia Mascolo
Author-email: eliamascolo94@gmail.com
Classifier: Programming Language :: Python :: 3
Classifier: License :: OSI Approved :: MIT License
Classifier: Operating System :: OS Independent
Requires-Python: >=3.6
License-File: LICENSE
